io_chunks/__init__.py
io_chunks/exceptions.py
io_chunks/raw_io_chunk.py
io_chunks-2.0.0.dist-info/LICENSE
io_chunks-2.0.0.dist-info/METADATA
io_chunks-2.0.0.dist-info/WHEEL
io_chunks-2.0.0.dist-info/top_level.txt
io_chunks-2.0.0.dist-info/RECORD
