Metadata-Version: 2.1
Name: io-chunks
Version: 2.0.0
Summary: Utilities to divide a buffer into smaller buffers
Author-email: David Caro <terseus@fastmail.com>
License: MIT
Project-URL: homepage, https://github.com/Terseus/python-io-chunks/
Keywords: io,library,development
Classifier: Development Status :: 5 - Production/Stable
Classifier: Intended Audience :: Developers
Classifier: License :: OSI Approved :: MIT License
Classifier: Operating System :: OS Independent
Classifier: Programming Language :: Python
Classifier: Topic :: Software Development :: Libraries :: Python Modules
License-File: LICENSE
